{
    "name": "esp32-evse",
    "version": "0.8.0",
    "funding_url": "https://github.com/sponsors/dzurikmiroslav",
    "new_install_prompt_erase": true,
    "builds": [
      {
        "chipFamily": "ESP32",
        "parts": [
          { "path": "https://dzurikmiroslav.github.io/esp32-evse/web-installer/esp32minimal.bin", "offset": 0 }
        ]
      },
      {
        "chipFamily": "ESP32-S2",
        "parts": [
          { "path": "https://dzurikmiroslav.github.io/esp32-evse/web-installer/esp32s2minimal.bin", "offset": 0 }
        ]
      },
      {
        "chipFamily": "ESP32-S3",
        "parts": [
          { "path": "https://dzurikmiroslav.github.io/esp32-evse/web-installer/esp32s3minimal.bin", "offset": 0 }
        ]
      }
    ]
  }
